<?xml version="1.0" encoding="UTF-8"?>
<?xml-stylesheet type="text/xsl" href="default.xsl"?>
<fr:tree
toc="true"
numbered="true"
show-heading="true"
show-metadata="true"
expanded="true"
root="false"
xmlns:fr="http://www.jonmsterling.com/jms-005P.xml"><fr:frontmatter><fr:anchor>548</fr:anchor><fr:addr
type="user">not-0001</fr:addr><fr:route>not-0001.xml</fr:route><fr:title
text="Methods of obtaining distributive law results">Methods of obtaining distributive law results</fr:title><fr:date><fr:year>2024</fr:year><fr:month>12</fr:month><fr:day>12</fr:day></fr:date><fr:authors><fr:author><fr:link
type="local"
href="chrisjpurdy.xml"
addr="chrisjpurdy"
title="Chris Purdy">Chris Purdy</fr:link></fr:author></fr:authors></fr:frontmatter><fr:mainmatter><fr:p>I've been reviewing the literature on distributive laws, specifically those papers that Dan Marsden mentioned, and have found some candidates for methods that we could attempt to adapt to finding monad container distributive laws:
  <fr:ul><fr:li>Generalising the "abides" property in <html:span
xmlns:html="http://www.w3.org/1999/xhtml"
class="link-reference"><fr:link
type="local"
href="zwartmarsden2022.xml"
addr="zwartmarsden2022"
title="No-Go Theorems for Distributive Laws">[zwartmarsden2022]</fr:link></html:span> to monad containers - looks like it would be some funky equation on positions in <fr:tex
display="inline"><![CDATA[\sigma ]]></fr:tex> shapes.</fr:li>
    <fr:li>Manes and Mulry I Theorem 4.3.4 mentions something about distributive laws between commutative monads - this might be adaptable.</fr:li>
    <fr:li>"Multiple constants" in <html:span
xmlns:html="http://www.w3.org/1999/xhtml"
class="link-reference"><fr:link
type="local"
href="zwartmarsden2022.xml"
addr="zwartmarsden2022"
title="No-Go Theorems for Distributive Laws">[zwartmarsden2022]</fr:link></html:span> would correspond to multiple shapes having singleton position sets.</fr:li>
    <fr:li>Manes and Mulry use "Kleisli strengths" to show distributive laws, we should see what those are in the case of monad containers.</fr:li></fr:ul></fr:p></fr:mainmatter><fr:backmatter><fr:tree
toc="false"
numbered="false"
show-heading="true"
show-metadata="false"
expanded="true"
root="false"
xmlns:fr="http://www.jonmsterling.com/jms-005P.xml"><fr:frontmatter><fr:title
text="References">References</fr:title><fr:authors /></fr:frontmatter><fr:mainmatter><fr:tree
toc="true"
numbered="false"
show-heading="true"
show-metadata="true"
expanded="false"
root="false"
xmlns:fr="http://www.jonmsterling.com/jms-005P.xml"><fr:frontmatter><fr:anchor>550</fr:anchor><fr:addr
type="user">zwartmarsden2022</fr:addr><fr:route>zwartmarsden2022.xml</fr:route><fr:title
text="No-Go Theorems for Distributive Laws">No-Go Theorems for Distributive Laws</fr:title><fr:taxon>Reference</fr:taxon><fr:date><fr:year>2022</fr:year></fr:date><fr:authors><fr:author>Maaike Zwart</fr:author><fr:author>Dan Marsden</fr:author></fr:authors><fr:meta
name="bibtex"><![CDATA[  @article{
    Zwart_Marsden_2022,
    title={No-Go Theorems for Distributive Laws}, 
    volume={Volume 18, Issue 1}, 
    rights={https://creativecommons.org/licenses/by/4.0}, 
    ISSN={1860-5974}, 
    DOI={10.46298/lmcs-18(1:13)2022}, 
    journal={Logical Methods in Computer Science}, 
    author={Zwart, Maaike and Marsden, Dan}, 
    year={2022}, 
    month=jan, 
    pages={6253}, 
    language={en} 
  }]]></fr:meta></fr:frontmatter><fr:mainmatter /><fr:backmatter /></fr:tree></fr:mainmatter><fr:backmatter /></fr:tree></fr:backmatter></fr:tree>